slims/__init__.py
slims/content.py
slims/criteria.py
slims/flowrun.py
slims/internal.py
slims/output.py
slims/slims.py
slims/step.py
slims/util.py
slims_python_api-7.2.0.dist-info/LICENSE
slims_python_api-7.2.0.dist-info/METADATA
slims_python_api-7.2.0.dist-info/WHEEL
slims_python_api-7.2.0.dist-info/top_level.txt
slims_python_api-7.2.0.dist-info/RECORD
