Metadata-Version: 2.2
Name: slims-python-api
Version: 7.2.0
Summary: A python api for SLims.
Home-page: http://www.genohm.com
Author: Genohm
Author-email: support@genohm.com
Maintainer: Genohm
Maintainer-email: support@genohm.com
License: TODO
Keywords: genohm,slims
Classifier: Development Status :: 4 - Beta
Classifier: Intended Audience :: Developers
Classifier: Natural Language :: English
Classifier: Operating System :: OS Independent
Classifier: Programming Language :: Python
Classifier: Programming Language :: Python :: 3
Classifier: Programming Language :: Python :: 3.13
Classifier: Programming Language :: Python :: Implementation :: CPython
Classifier: Programming Language :: Python :: Implementation :: PyPy
Classifier: Topic :: Internet :: WWW/HTTP :: WSGI :: Application
License-File: LICENSE
Requires-Dist: flask>=3.1.0
Requires-Dist: requests>=2.32.3
Requires-Dist: requests_oauthlib>=2.0.0
Requires-Dist: deprecation>=2.0.0
Dynamic: author
Dynamic: author-email
Dynamic: classifier
Dynamic: description
Dynamic: description-content-type
Dynamic: home-page
Dynamic: keywords
Dynamic: license
Dynamic: maintainer
Dynamic: maintainer-email
Dynamic: requires-dist
Dynamic: summary
